orchestra/__init__.py
orchestra/_internals/__init__.py
orchestra/_internals/common/__init__.py
orchestra/_internals/common/models/__init__.py
orchestra/_internals/common/models/basemodels.py
orchestra/_internals/common/models/config.py
orchestra/_internals/common/models/exceptions.py
orchestra/_internals/common/models/granularity.py
orchestra/_internals/common/models/pagination.py
orchestra/_internals/common/models/sort.py
orchestra/_internals/common/utils.py
orchestra/_internals/elements/__init__.py
orchestra/_internals/elements/certificates_interface.py
orchestra/_internals/elements/element_interface.py
orchestra/_internals/elements/element_type_interface.py
orchestra/_internals/elements/events_interface.py
orchestra/_internals/elements/grpc.py
orchestra/_internals/elements/logging_interface.py
orchestra/_internals/elements/telemetry_interface.py
orchestra/_internals/elements/twin_interface.py
orchestra/_internals/rpc/__init__.py
orchestra/_internals/rpc/orchestra/__init__.py
orchestra/_internals/rpc/orchestra/certificates_pb2.py
orchestra/_internals/rpc/orchestra/certificates_pb2.pyi
orchestra/_internals/rpc/orchestra/certificates_pb2_grpc.py
orchestra/_internals/rpc/orchestra/certificates_public_pb2.py
orchestra/_internals/rpc/orchestra/certificates_public_pb2.pyi
orchestra/_internals/rpc/orchestra/certificates_public_pb2_grpc.py
orchestra/_internals/rpc/orchestra/element_logs_pb2.py
orchestra/_internals/rpc/orchestra/element_logs_pb2.pyi
orchestra/_internals/rpc/orchestra/element_logs_pb2_grpc.py
orchestra/_internals/rpc/orchestra/element_telemetry_pb2.py
orchestra/_internals/rpc/orchestra/element_telemetry_pb2.pyi
orchestra/_internals/rpc/orchestra/element_telemetry_pb2_grpc.py
orchestra/_internals/rpc/orchestra/element_twins_pb2.py
orchestra/_internals/rpc/orchestra/element_twins_pb2.pyi
orchestra/_internals/rpc/orchestra/element_twins_pb2_grpc.py
orchestra/_internals/rpc/orchestra/element_types_pb2.py
orchestra/_internals/rpc/orchestra/element_types_pb2.pyi
cthingsco_orchestra-0.7.0.dist-info/LICENSE
cthingsco_orchestra-0.7.0.dist-info/METADATA
cthingsco_orchestra-0.7.0.dist-info/WHEEL
cthingsco_orchestra-0.7.0.dist-info/RECORD
