Metadata-Version: 2.1
Name: cthingsco-orchestra
Version: 0.7.0
Summary: Orchestra SDK and bindings for Python.
License: GNU Lesser General Public License v3 (LGPLv3)
Author: CTHINGS.CO
Author-email: contact@cthings.co
Requires-Python: >=3.10
Classifier: Development Status :: 4 - Beta
Classifier: License :: OSI Approved :: GNU Lesser General Public License v3 (LGPLv3)
Classifier: License :: Other/Proprietary License
Classifier: Programming Language :: Python
Classifier: Programming Language :: Python :: 3
Classifier: Programming Language :: Python :: 3.10
Classifier: Programming Language :: Python :: 3.11
Classifier: Programming Language :: Python :: 3.12
Classifier: Programming Language :: Python :: 3.13
Classifier: Programming Language :: Python :: 3.9
Classifier: Topic :: Software Development
Requires-Dist: futurist (>=2.4.1,<3.0.0)
Requires-Dist: grpcio (>=1.56.0,<2.0.0)
Requires-Dist: orjson (>=3.9.1,<4.0.0)
Requires-Dist: protobuf (>=4.23.3,<5.0.0)
Requires-Dist: pydantic (>=2.12.5,<3.0.0)
Requires-Dist: pydantic-settings (>=2.12.0,<3.0.0)
Requires-Dist: pymongo (>=4.15.1,<5.0.0)
Project-URL: Documentation, https://docs.orchestra.cthings.co
Project-URL: Homepage, https://cthings.co
